dftd_labeler/__init__.py
dftd_labeler/labeler.py
tests/__init__.py
tests/test_dftd_labeler.py
dftd_labeler-0.1.2.dist-info/METADATA
dftd_labeler-0.1.2.dist-info/WHEEL
dftd_labeler-0.1.2.dist-info/entry_points.txt
dftd_labeler-0.1.2.dist-info/top_level.txt
dftd_labeler-0.1.2.dist-info/RECORD
