Metadata-Version: 2.1
Name: dftd-labeler
Version: 0.1.2
Summary: A convenience tool to label structures with DFT dispersion corrections.
Home-page: https://github.com/tcnicholas/dftd_labeler
Author: Thomas C Nicholas
Author-email: thomas.nicholas@chem.ox.ac.uk
Classifier: Development Status :: 3 - Alpha
Classifier: Intended Audience :: Science/Research
Classifier: License :: OSI Approved :: MIT License
Classifier: Programming Language :: Python :: 3.9
Requires-Dist: ase
